mne_connectivity/__init__.py
mne_connectivity/_version.py
mne_connectivity/base.py
mne_connectivity/conftest.py
mne_connectivity/effective.py
mne_connectivity/envelope.py
mne_connectivity/io.py
mne_connectivity/datasets/__init__.py
mne_connectivity/datasets/frequency.py
mne_connectivity/spectral/__init__.py
mne_connectivity/spectral/epochs.py
mne_connectivity/spectral/epochs_bivariate.py
mne_connectivity/spectral/epochs_multivariate.py
mne_connectivity/spectral/smooth.py
mne_connectivity/spectral/time.py
mne_connectivity/spectral/tests/test_spectral.py
mne_connectivity/tests/__init__.py
mne_connectivity/tests/test_connectivity.py
mne_connectivity/tests/test_datasets.py
mne_connectivity/tests/test_effective.py
mne_connectivity/tests/test_envelope.py
mne_connectivity/tests/test_utils.py
mne_connectivity/utils/__init__.py
mne_connectivity/utils/docs.py
mne_connectivity/utils/utils.py
mne_connectivity/vector_ar/__init__.py
mne_connectivity/vector_ar/model_selection.py
mne_connectivity/vector_ar/utils.py
mne_connectivity/vector_ar/var.py
mne_connectivity/vector_ar/tests/test_var.py
mne_connectivity/viz/_3d.py
mne_connectivity/viz/__init__.py
mne_connectivity/viz/circle.py
mne_connectivity/viz/tests/test_3d.py
mne_connectivity/viz/tests/test_circle.py
mne_connectivity-0.7.0.dist-info/LICENSE
mne_connectivity-0.7.0.dist-info/METADATA
mne_connectivity-0.7.0.dist-info/WHEEL
mne_connectivity-0.7.0.dist-info/top_level.txt
mne_connectivity-0.7.0.dist-info/RECORD
