Metadata-Version: 2.1
Name: mne-connectivity
Version: 0.7.0
Summary: mne-connectivity: A module for connectivity data analysis with MNE.
Maintainer-email: Adam Li <adam.li@columbia.edu>
License: BSD 3-Clause License
Project-URL: documentation, https://mne.tools/mne-connectivity
Project-URL: source, https://github.com/mne-tools/mne-connectivity
Project-URL: tracker, https://github.com/mne-tools/mne-connectivity/issues
Keywords: connectivity,eeg,ieeg,meg,neuroscience
Classifier: Intended Audience :: Developers
Classifier: Intended Audience :: Science/Research
Classifier: License :: OSI Approved :: BSD License
Classifier: Natural Language :: English
Classifier: Operating System :: MacOS
Classifier: Operating System :: Microsoft :: Windows
Classifier: Operating System :: Unix
Classifier: Programming Language :: Python :: 3 :: Only
Classifier: Programming Language :: Python :: 3.10
Classifier: Programming Language :: Python :: 3.11
Classifier: Programming Language :: Python :: 3.12
Classifier: Programming Language :: Python :: 3.9
Classifier: Topic :: Scientific/Engineering
Classifier: Topic :: Software Development
Requires-Python: >=3.9
License-File: LICENSE
Requires-Dist: mne>=1.6
Requires-Dist: netCDF4>=1.6.5
Requires-Dist: numpy>=1.21
Requires-Dist: pandas>=1.3.2
Requires-Dist: scipy>=1.4.0
Requires-Dist: tqdm
Requires-Dist: xarray>=2023.11.0
Provides-Extra: all
Requires-Dist: mne-connectivity[build]; extra == "all"
Requires-Dist: mne-connectivity[doc]; extra == "all"
Requires-Dist: mne-connectivity[gui]; extra == "all"
Requires-Dist: mne-connectivity[style]; extra == "all"
Requires-Dist: mne-connectivity[test]; extra == "all"
Provides-Extra: build
Requires-Dist: build; extra == "build"
Requires-Dist: twine; extra == "build"
Provides-Extra: doc
Requires-Dist: memory-profiler; extra == "doc"
Requires-Dist: mne-bids; extra == "doc"
Requires-Dist: mne-connectivity[gui]; extra == "doc"
Requires-Dist: nibabel; extra == "doc"
Requires-Dist: nilearn; extra == "doc"
Requires-Dist: numpydoc; extra == "doc"
Requires-Dist: pooch; extra == "doc"
Requires-Dist: pydata-sphinx-theme==0.14.1; extra == "doc"
Requires-Dist: PyQt6; extra == "doc"
Requires-Dist: sphinx; extra == "doc"
Requires-Dist: sphinx-copybutton; extra == "doc"
Requires-Dist: sphinx-design; extra == "doc"
Requires-Dist: sphinx-gallery; extra == "doc"
Requires-Dist: sphinx-issues; extra == "doc"
Requires-Dist: sphinx_autodoc_typehints; extra == "doc"
Requires-Dist: sphinxcontrib-bibtex; extra == "doc"
Provides-Extra: full
Requires-Dist: mne-connectivity[all]; extra == "full"
Provides-Extra: gui
Requires-Dist: h5netcdf; extra == "gui"
Requires-Dist: matplotlib; extra == "gui"
Requires-Dist: mne-qt-browser>=0.6.0; extra == "gui"
Requires-Dist: PyQt6; extra == "gui"
Requires-Dist: pyvista; extra == "gui"
Requires-Dist: pyvistaqt; extra == "gui"
Requires-Dist: qtpy; extra == "gui"
Requires-Dist: sip; extra == "gui"
Requires-Dist: vtk; extra == "gui"
Provides-Extra: style
Requires-Dist: pre-commit; extra == "style"
Requires-Dist: codespell; extra == "style"
Requires-Dist: isort; extra == "style"
Requires-Dist: pydocstyle; extra == "style"
Requires-Dist: pydocstyle[toml]; extra == "style"
Requires-Dist: rstcheck; extra == "style"
Requires-Dist: ruff; extra == "style"
Requires-Dist: toml-sort; extra == "style"
Requires-Dist: yamllint; extra == "style"
Provides-Extra: test
Requires-Dist: pytest-timeout; extra == "test"
Requires-Dist: joblib; extra == "test"
Requires-Dist: mne-bids; extra == "test"
Requires-Dist: mne-connectivity[gui]; extra == "test"
Requires-Dist: pandas; extra == "test"
Requires-Dist: pymatreader; extra == "test"
Requires-Dist: PyQt6; extra == "test"
Requires-Dist: pytest-cov; extra == "test"
Requires-Dist: pytest<8.0.0; extra == "test"
Requires-Dist: statsmodels; extra == "test"
